svdcompressionimage/__init__.py
svdcompressionimage/compression_algorithm.py
svdcompressionimage-0.1.2.dist-info/LICENSE.txt
svdcompressionimage-0.1.2.dist-info/METADATA
svdcompressionimage-0.1.2.dist-info/WHEEL
svdcompressionimage-0.1.2.dist-info/top_level.txt
svdcompressionimage-0.1.2.dist-info/RECORD
