Metadata-Version: 2.1
Name: svdcompressionimage
Version: 0.1.2
Summary: A Python package for image compression using Singular Value Decomposition (SVD), applying an efficient block-based method to reduce storage while retaining visual quality.
Author: Katie Wen-Ling Kuo
Author-email: katie20030705@gmail.com
License: MIT
Classifier: License :: OSI Approved :: MIT License
Classifier: Programming Language :: Python :: 3
Requires-Python: >=3.6
License-File: LICENSE.txt
Requires-Dist: numpy
Requires-Dist: pillow
Requires-Dist: scipy
Requires-Dist: scikit-learn
